{
  "COM-11101": {
    "semestre": 1,
    "nombre": "Algoritmos y Programas",
    "creditos": 9,
    "prerreqs": [],
    "coreqs": [],
    "estado": 0
  },
  "MAT-14250": {
    "semestre": 1,
    "nombre": "Geometría Vectorial",
    "creditos": 6,
    "prerreqs": [],
    "coreqs": [],
    "estado": 0
  },
  "MAT-14100": {
    "semestre": 1,
    "nombre": "Cálculo Diferencial e Integral I",
    "creditos": 8,
    "prerreqs": [],
    "coreqs": [],
    "estado": 0
  },
  "LEN-12701": {
    "semestre": 1,
    "nombre": "Estrategias de Comunicación Escrita",
    "creditos": 6,
    "prerreqs": [],
    "coreqs": [],
    "estado": 0
  },
  "ECO-11101": {
    "semestre": 1,
    "nombre": "Economía I",
    "creditos": 6,
    "prerreqs": [],
    "coreqs": [],
    "estado": 0
  },
  "EGN-17121": {
    "semestre": 1,
    "nombre": "Ideas e Instituciones Políticas y Sociales I",
    "creditos": 6,
    "prerreqs": [],
    "coreqs": [],
    "estado": 0
  },
  "MAT-14280": {
    "semestre": 2,
    "nombre": "Pensamiento Matemático",
    "creditos": 6,
    "prerreqs": [],
    "coreqs": [],
    "estado": 0
  },
  "EST-24127": {
    "semestre": 5,
    "nombre": "Cálculo de Probabilidades II",
    "creditos": 6,
    "prerreqs": [
      "EST-24126"
    ],
    "coreqs": [],
    "estado": 0
  },
  "EST-14103": {
    "semestre": 6,
    "nombre": "Estadística Matemática",
    "creditos": 8,
    "prerreqs": [
      "EST-24127"
    ],
    "coreqs": [],
    "estado": 0
  },
  "EST-24124": {
    "semestre": 7,
    "nombre": "Métodos Lineales",
    "creditos": 6,
    "prerreqs": [
      "EST-14103"
    ],
    "coreqs": [],
    "estado": 0
  },
  "ECO-10521": {
    "semestre": 7,
    "nombre": "Inferencia Causal",
    "creditos": 6,
    "prerreqs": [
      "EST-14103"
    ],
    "coreqs": [],
    "estado": 0
  },
  "EST-24125": {
    "semestre": 8,
    "nombre": "Métodos Multivariados",
    "creditos": 6,
    "prerreqs": [
      "EST-14103"
    ],
    "coreqs": [],
    "estado": 0
  },
  "EST-24112": {
    "semestre": 9,
    "nombre": "Estadística Bayesiana",
    "creditos": 6,
    "prerreqs": [
      "EST-14103"
    ],
    "coreqs": [],
    "estado": 0
  }
}